{
  "job_info": {
    "job_id": "6a580d2b08442f441bbb17ee",
    "job_submission": {
      "job_name": "cmpo_v2_smoke_pglib_case14_ieee__storm_forced_islanding_BUS3_MG-BUS4_MG__from__storm_forced_islanding_BUS3_MG-BUS4_MG-BUS9_MG_r004_n1",
      "job_tags": [
        "cmpo",
        "phase3",
        "dirac3",
        "qci_fit"
      ],
      "problem_config": {
        "normalized_qudit_hamiltonian_optimization": {
          "polynomial_file_id": "6a580d2bff2f309fb9d02d12"
        }
      },
      "device_config": {
        "dirac-3_normalized_qudit": {
          "num_samples": 1,
          "relaxation_schedule": 1,
          "sum_constraint": 10000
        }
      }
    },
    "job_status": {
      "submitted_at_rfc3339nano": "2026-07-15T22:43:55.521Z",
      "queued_at_rfc3339nano": "2026-07-15T22:43:55.522Z",
      "running_at_rfc3339nano": "2026-07-15T22:50:31.617Z",
      "completed_at_rfc3339nano": "2026-07-15T22:50:47.637Z"
    },
    "job_result": {
      "file_id": "6a580ec7ff2f309fb9d02d6c",
      "device_usage_s": 15
    }
  },
  "status": "COMPLETED",
  "results": {
    "counts": [
      1
    ],
    "energies": [
      -538297
    ],
    "solutions": [
      [
        213.1147308,
        234.9813538,
        109.8996201,
        137.9334259,
        0,
        0,
        0,
        0,
        1.1691744,
        0,
        0,
        254.6461639,
        317.0297241,
        155.8592529,
        309.4893799,
        0,
        0,
        0,
        0,
        1.8200021,
        0,
        0,
        56.8883591,
        135.7196808,
        176.865097,
        288.0732117,
        0,
        0,
        3e-07,
        0,
        1.6023453,
        0,
        0,
        221.4759979,
        270.674408,
        165.4478912,
        362.6054993,
        0,
        0,
        3e-07,
        0,
        2.2085884,
        0,
        0,
        134.8968201,
        245.1120453,
        194.7492371,
        392.1096802,
        1e-07,
        0,
        0,
        0,
        2.3348098,
        0,
        0,
        139.2726898,
        218.4283905,
        170.1862488,
        434.4840698,
        0,
        0,
        0,
        0,
        1.9714836,
        0,
        0,
        169.5512085,
        292.7667236,
        162.4273834,
        141.0761719,
        0,
        0,
        0,
        0,
        1.9260542,
        0,
        0,
        123.3592453,
        96.2013855,
        30.2611408,
        225.7531433,
        2e-07,
        0,
        0,
        0,
        1.3142861,
        0,
        0,
        128.1401672,
        248.4481354,
        174.9216766,
        279.5680542,
        0,
        0,
        0,
        0,
        1.8906325,
        0,
        0,
        98.2814484,
        202.0805206,
        171.4296112,
        305.4372559,
        0,
        0,
        0,
        0,
        1.8353153,
        0,
        0,
        105.9105911,
        216.1938477,
        169.5642853,
        335.6897583,
        0,
        0,
        0,
        0,
        2.1290112,
        0,
        0,
        164.1139374,
        250.020813,
        139.2127228,
        407.8986816,
        0,
        0,
        0,
        0,
        1.5479808,
        0,
        0
      ]
    ]
  }
}