{
  "job_info": {
    "job_id": "6a5810c508442f441bbb1823",
    "job_submission": {
      "job_name": "hybrid_smoke_pglib_case30_ieee__hybrid__demand_surge_BUS5_MG-BUS7_MG__from__demand_surge_BUS2_MG-BUS5_MG-BUS7_MG_r004_n1",
      "job_tags": [
        "cmpo",
        "phase3",
        "dirac3",
        "qci_fit"
      ],
      "problem_config": {
        "normalized_qudit_hamiltonian_optimization": {
          "polynomial_file_id": "6a5810c5ff2f309fb9d02dff"
        }
      },
      "device_config": {
        "dirac-3_normalized_qudit": {
          "num_samples": 1,
          "relaxation_schedule": 1,
          "sum_constraint": 10000
        }
      }
    },
    "job_status": {
      "submitted_at_rfc3339nano": "2026-07-15T22:59:17.242Z",
      "queued_at_rfc3339nano": "2026-07-15T22:59:17.242Z",
      "running_at_rfc3339nano": "2026-07-15T23:00:32.879Z",
      "completed_at_rfc3339nano": "2026-07-15T23:00:34.791Z"
    },
    "job_result": {
      "file_id": "6a581112ff2f309fb9d02e4d",
      "device_usage_s": 1
    }
  },
  "status": "COMPLETED",
  "results": {
    "counts": [
      1
    ],
    "energies": [
      -40068.8203125
    ],
    "solutions": [
      [
        0,
        0,
        0,
        7e-07,
        4.4e-06,
        0,
        8.56e-05,
        5.24e-05,
        2.87e-05,
        0.2620152,
        0.0002683,
        0.7504424,
        1062.4448242,
        0,
        0,
        0,
        3e-07,
        1.5e-06,
        0,
        0.3798895,
        0.0001829,
        0.7361298,
        1381.1774902,
        0,
        0,
        0,
        0,
        0,
        0,
        0.6062975,
        0.0002673,
        0.8085096,
        956.1997681,
        0,
        0,
        0,
        1.71e-05,
        4.45e-05,
        2.4e-06,
        0.1985664,
        0.0021278,
        0.6335033,
        743.7114258,
        0,
        0,
        0,
        1.4e-06,
        2.2e-06,
        0,
        0.7283661,
        0.0009057,
        0.6378906,
        849.9550171,
        0,
        0,
        0,
        8.94e-05,
        0.0002568,
        0.0045865,
        0.0058534,
        0.0002921,
        0.7306959,
        212.4887543,
        2.3e-06,
        1.3e-06,
        0,
        0.0006675,
        0.0014028,
        0.0035045,
        1.0443629,
        3.39e-05,
        0.8463246,
        956.1997681,
        0,
        0,
        0,
        4.46e-05,
        0.0001042,
        7.2e-06,
        0.0071615,
        0.0001438,
        0.7365984,
        1062.4448242,
        0,
        0,
        0,
        3e-07,
        2e-07,
        0,
        0.6421689,
        0.0001463,
        0.5107779,
        318.7331543,
        0,
        0,
        0,
        8.72e-05,
        0.0001048,
        1e-07,
        0.0589578,
        0.0002183,
        0.7651835,
        1062.4448242,
        0,
        0,
        0,
        1.12e-05,
        1.05e-05,
        0,
        0.4131141,
        5.93e-05,
        0.5090285,
        318.7331543,
        0,
        1e-07,
        0,
        6e-06,
        5.3e-06,
        2e-06,
        0.2265778,
        0.0007886,
        0.7664201,
        1062.4448242
      ]
    ]
  }
}